{"version":2,"kind":"Notebook","sha256":"47f90146e0604e0c81a361c77f51325e8b64995d949a4b0ed055662ff1b4fceb","slug":"hda-pystac-client-1","location":"/HDA/PySTAC/HDA-PyStac-Client.ipynb","dependencies":[],"frontmatter":{"title":"HDA PySTAC-Client Introduction","content_includes_title":true,"kernelspec":{"name":"python_dedl","display_name":"Python DEDL","language":"python"},"numbering":{"title":{"offset":2}},"thumbnail":"/b27bd30f978ddf0848f3ea0942070886.jpeg","exports":[{"format":"ipynb","filename":"HDA-PyStac-Client.ipynb","url":"/HDA-PyStac-Client-35a9618b4a4bcd0feb68f8c62f805792.ipynb"}]},"widgets":{},"mdast":{"type":"root","children":[{"type":"block","kind":"notebook-content","data":{"tags":[]},"children":[{"type":"image","url":"/b27bd30f978ddf0848f3ea0942070886.jpeg","position":{"start":{"line":1,"column":1},"end":{"line":1,"column":1}},"key":"ZH2wpwrG1y","urlSource":"https://github.com/destination-earth/DestinE-DataLake-Lab/blob/main/img/DestinE-banner.jpg?raw=true"}],"visibility":"show","key":"au0ODBaLrD"},{"type":"block","kind":"notebook-content","children":[{"type":"paragraph","position":{"start":{"line":1,"column":1},"end":{"line":3,"column":1}},"children":[{"type":"strong","position":{"start":{"line":1,"column":1},"end":{"line":1,"column":1}},"children":[{"type":"text","value":"Author","position":{"start":{"line":1,"column":1},"end":{"line":1,"column":1}},"key":"JC2zhTodTv"}],"key":"atOSV9F957"},{"type":"text","value":": EUMETSAT ","position":{"start":{"line":1,"column":1},"end":{"line":1,"column":1}},"key":"AecE6pbWG3"},{"type":"break","key":"UygGEBPkf9"},{"type":"text","value":"\n","position":{"start":{"line":1,"column":1},"end":{"line":1,"column":1}},"key":"BHJ1JmQysQ"},{"type":"strong","position":{"start":{"line":1,"column":1},"end":{"line":1,"column":1}},"children":[{"type":"text","value":"Copyright","position":{"start":{"line":1,"column":1},"end":{"line":1,"column":1}},"key":"avIBufDJpM"}],"key":"fDvCRem0hE"},{"type":"text","value":": 2024 EUMETSAT ","position":{"start":{"line":1,"column":1},"end":{"line":1,"column":1}},"key":"UqjUI6huKj"},{"type":"break","key":"j96e31q8vN"},{"type":"text","value":"\n","position":{"start":{"line":1,"column":1},"end":{"line":1,"column":1}},"key":"RoaClAbNFl"},{"type":"strong","position":{"start":{"line":1,"column":1},"end":{"line":1,"column":1}},"children":[{"type":"text","value":"Licence","position":{"start":{"line":1,"column":1},"end":{"line":1,"column":1}},"key":"TFpwmTf6JZ"}],"key":"bnU2vveDPc"},{"type":"text","value":": MIT ","position":{"start":{"line":1,"column":1},"end":{"line":1,"column":1}},"key":"akZJ2Xwwwy"},{"type":"break","key":"AyrOWKh1W7"}],"key":"JVFGU5sWCM"},{"type":"heading","depth":1,"position":{"start":{"line":5,"column":1},"end":{"line":5,"column":1}},"children":[{"type":"text","value":"HDA PySTAC-Client Introduction","position":{"start":{"line":5,"column":1},"end":{"line":5,"column":1}},"key":"YXb1oa3IPK"}],"identifier":"hda-pystac-client-introduction","label":"HDA PySTAC-Client Introduction","html_id":"hda-pystac-client-introduction","implicit":true,"key":"JXrautHeWX"},{"type":"paragraph","position":{"start":{"line":8,"column":1},"end":{"line":9,"column":1}},"children":[{"type":"text","value":"This notebook shows the basic use of DestinE Data Lake Harmonised Data Access using pystac-client.\nIt will include iterating through Collections and Items, and perform simple spatio-temporal searches.","position":{"start":{"line":8,"column":1},"end":{"line":8,"column":1}},"key":"uSG0QDvOVo"}],"key":"QV87eCKFog"}],"key":"PtvhtkDPC2"},{"type":"block","kind":"notebook-content","children":[{"type":"heading","depth":2,"position":{"start":{"line":1,"column":1},"end":{"line":1,"column":1}},"children":[{"type":"text","value":"Obtain DEDL Access Token to use the HDA service","position":{"start":{"line":1,"column":1},"end":{"line":1,"column":1}},"key":"V3kIEbSTN5"}],"identifier":"obtain-dedl-access-token-to-use-the-hda-service","label":"Obtain DEDL Access Token to use the HDA service","html_id":"obtain-dedl-access-token-to-use-the-hda-service","implicit":true,"key":"vUk8iOEzT1"}],"key":"B7GLC3KcT9"},{"type":"block","kind":"notebook-code","data":{"tags":[]},"children":[{"type":"code","lang":"python","executable":true,"value":"pip install --quiet --upgrade destinelab","visibility":"show","key":"jOTg6yq4M9"},{"type":"output","id":"G2WxM2ilUXkmHm8yWAZl2","data":[{"name":"stdout","output_type":"stream","text":"Note: you may need to restart the kernel to use updated packages.\n"}],"visibility":"show","key":"MgeVLrxnRQ"}],"visibility":"show","key":"RUmAK78fNh"},{"type":"block","kind":"notebook-code","data":{"tags":[]},"children":[{"type":"code","lang":"python","executable":true,"value":"import requests\nimport json\nimport os\nfrom getpass import getpass\nimport destinelab as deauth","visibility":"show","key":"xn8uNW5XJE"},{"type":"output","id":"exTnk79GIyFjk3HHfwEOg","data":[],"visibility":"show","key":"Fxn4ZGzAzl"}],"visibility":"show","key":"J3PxKO3qwz"},{"type":"block","kind":"notebook-code","data":{"tags":[]},"children":[{"type":"code","lang":"python","executable":true,"value":"DESP_USERNAME = input(\"Please input your DESP username or email: \")\nDESP_PASSWORD = getpass(\"Please input your DESP password: \")\n\nauth = deauth.AuthHandler(DESP_USERNAME, DESP_PASSWORD)\naccess_token = auth.get_token()\nif access_token is not None:\n    print(\"DEDL/DESP Access Token Obtained Successfully\")\nelse:\n    print(\"Failed to Obtain DEDL/DESP Access Token\")\n\nauth_headers = {\"Authorization\": f\"Bearer {access_token}\"}","visibility":"show","key":"ibntDgmkOw"},{"type":"output","id":"e9ohHqcbPOFnSR-_dQUrb","data":[{"name":"stdin","output_type":"stream","text":"Please input your DESP username or email:  eum-dedl-user\nPlease input your DESP password:  ········\n"},{"name":"stdout","output_type":"stream","text":"Response code: 200\nDEDL/DESP Access Token Obtained Successfully\n"}],"visibility":"show","key":"S3ai4udbcR"}],"visibility":"show","key":"C2eSAESny9"},{"type":"block","kind":"notebook-content","children":[{"type":"heading","depth":2,"position":{"start":{"line":1,"column":1},"end":{"line":1,"column":1}},"children":[{"type":"text","value":"Set username and password as environment variables to be used for DEDL data access","position":{"start":{"line":1,"column":1},"end":{"line":1,"column":1}},"key":"crwtgTz2Aq"}],"identifier":"set-username-and-password-as-environment-variables-to-be-used-for-dedl-data-access","label":"Set username and password as environment variables to be used for DEDL data access","html_id":"set-username-and-password-as-environment-variables-to-be-used-for-dedl-data-access","implicit":true,"key":"sWFNyBdUNg"}],"key":"RNzaYYabgC"},{"type":"block","kind":"notebook-code","data":{"tags":[]},"children":[{"type":"code","lang":"python","executable":true,"value":"import os\n\nos.environ[\"EODAG__DEDL__AUTH__CREDENTIALS__USERNAME\"] = DESP_USERNAME\nos.environ[\"EODAG__DEDL__AUTH__CREDENTIALS__PASSWORD\"] = DESP_PASSWORD","visibility":"show","key":"MzCtuNVDZ2"},{"type":"output","id":"dj3_CL-3TbdwgkRL5uBHq","data":[],"visibility":"show","key":"tZccR1bUPV"}],"visibility":"show","key":"eE644SjYI0"},{"type":"block","kind":"notebook-content","children":[{"type":"heading","depth":1,"position":{"start":{"line":1,"column":1},"end":{"line":1,"column":1}},"children":[{"type":"text","value":"Create pystac client object for HDA STAC API","position":{"start":{"line":1,"column":1},"end":{"line":1,"column":1}},"key":"gZmMpy1itz"}],"identifier":"create-pystac-client-object-for-hda-stac-api","label":"Create pystac client object for HDA STAC API","html_id":"create-pystac-client-object-for-hda-stac-api","implicit":true,"key":"zIXgfd9VwI"},{"type":"paragraph","position":{"start":{"line":2,"column":1},"end":{"line":2,"column":1}},"children":[{"type":"text","value":"We first connect to an API by retrieving the root catalog, or landing page, of the API with the ","position":{"start":{"line":2,"column":1},"end":{"line":2,"column":1}},"key":"cHpogD60n0"},{"type":"link","url":"http://Client.open","position":{"start":{"line":2,"column":1},"end":{"line":2,"column":1}},"children":[{"type":"text","value":"Client.open","position":{"start":{"line":2,"column":1},"end":{"line":2,"column":1}},"key":"mGNKCeGcdU"}],"urlSource":"http://Client.open","key":"czLydr5aYn"},{"type":"text","value":" function.","position":{"start":{"line":2,"column":1},"end":{"line":2,"column":1}},"key":"wSxUatV172"}],"key":"Hudn6RPtdz"}],"key":"FkGkXRZUit"},{"type":"block","kind":"notebook-code","data":{"tags":[]},"children":[{"type":"code","lang":"python","executable":true,"value":"from pystac_client import Client\n\nHDA_API_URL = \"https://hda.data.destination-earth.eu/stac\"\ncat = Client.open(HDA_API_URL, headers=auth_headers)","visibility":"show","key":"p62g3B8y94"},{"type":"output","id":"BnBijDzccjH26t89Egm7t","data":[],"visibility":"show","key":"iTymDkPM7i"}],"visibility":"show","key":"c88TkaMqGw"},{"type":"block","kind":"notebook-content","children":[{"type":"heading","depth":2,"position":{"start":{"line":1,"column":1},"end":{"line":1,"column":1}},"children":[{"type":"text","value":"Query all available collections","position":{"start":{"line":1,"column":1},"end":{"line":1,"column":1}},"key":"O3Ees6LlXM"}],"identifier":"query-all-available-collections","label":"Query all available collections","html_id":"query-all-available-collections","implicit":true,"key":"NUyh6YV1K0"},{"type":"paragraph","position":{"start":{"line":2,"column":1},"end":{"line":3,"column":1}},"children":[{"type":"text","value":"As with a static catalog the get_collections function will iterate through the Collections in the Catalog.\nNotice that because this is an API it can get all the Collections through a single call, rather than having to fetch each one individually.","position":{"start":{"line":2,"column":1},"end":{"line":2,"column":1}},"key":"fmgYDlJVj4"}],"key":"gQ7FRbQrHq"}],"key":"fwApWZ7fBN"},{"type":"block","kind":"notebook-code","data":{"tags":[]},"children":[{"type":"code","lang":"python","executable":true,"value":"from rich.console import Console\nimport rich.table\n\nconsole = Console()\n\nhda_collections = cat.get_collections()\n\ntable = rich.table.Table(title=\"HDA collections\", expand=True)\ntable.add_column(\"ID\", style=\"cyan\", justify=\"right\",no_wrap=True)\ntable.add_column(\"Title\", style=\"violet\", no_wrap=True)\nfor collection in hda_collections:\n    table.add_row(collection.id, collection.title)\nconsole.print(table)","visibility":"show","key":"XoFZ5pgQoe"},{"type":"output","id":"83W7c0XEW6uWXGwBe4XLC","data":[{"output_type":"display_data","metadata":{},"data":{"text/html":{"content_type":"text/html","hash":"78119a4dcf5d0b2dd8d9cbd59a1a6341","path":"/78119a4dcf5d0b2dd8d9cbd59a1a6341.html"},"text/plain":{"content_type":"text/plain","hash":"643be1662b8f78b3db1cc7f261709ada","path":"/643be1662b8f78b3db1cc7f261709ada.txt"}}}],"visibility":"show","key":"Fn8ZTvnJKF"}],"visibility":"show","key":"QnKRZ83YCV"},{"type":"block","kind":"notebook-content","children":[{"type":"heading","depth":2,"position":{"start":{"line":1,"column":1},"end":{"line":1,"column":1}},"children":[{"type":"text","value":"Obtain provider information for each individual collection","position":{"start":{"line":1,"column":1},"end":{"line":1,"column":1}},"key":"Pml3ZCSj1V"}],"identifier":"obtain-provider-information-for-each-individual-collection","label":"Obtain provider information for each individual collection","html_id":"obtain-provider-information-for-each-individual-collection","implicit":true,"key":"YFErHKSp7w"}],"key":"ZAmwVib4SB"},{"type":"block","kind":"notebook-code","data":{"tags":[]},"children":[{"type":"code","lang":"python","executable":true,"value":"table = rich.table.Table(title=\"HDA collections | Providers\", expand=True)\ntable.add_column(\"Title\", style=\"cyan\", justify=\"right\", no_wrap=True)\ntable.add_column(\"Provider\", style=\"violet\", no_wrap=True)\n\nhda_collections = cat.get_collections()\n\nfor collection in hda_collections:\n    collection_details = cat.get_collection(collection.id)\n    provider = ','.join(str(x.name) for x in collection_details.providers)\n    table.add_row(collection_details.title, provider)\nconsole.print(table)","visibility":"show","key":"fmjZwfRg7v"},{"type":"output","id":"9dXZV5NvRDtEAzApWVmr4","data":[{"output_type":"display_data","metadata":{},"data":{"text/html":{"content_type":"text/html","hash":"8c35c86f5252240bbcf78869216eaebf","path":"/8c35c86f5252240bbcf78869216eaebf.html"},"text/plain":{"content_type":"text/plain","hash":"c61d2e2cc31cbccb41a2f517560fc8da","path":"/c61d2e2cc31cbccb41a2f517560fc8da.txt"}}}],"visibility":"show","key":"xvuAWgEMKq"}],"visibility":"show","key":"Fk7wegZSOK"},{"type":"block","kind":"notebook-content","children":[{"type":"heading","depth":2,"position":{"start":{"line":1,"column":1},"end":{"line":1,"column":1}},"children":[{"type":"text","value":"Inspect Items of a Collection","position":{"start":{"line":1,"column":1},"end":{"line":1,"column":1}},"key":"ocwkDZEYAp"}],"identifier":"inspect-items-of-a-collection","label":"Inspect Items of a Collection","html_id":"inspect-items-of-a-collection","implicit":true,"key":"woyDr1lZVK"},{"type":"paragraph","position":{"start":{"line":2,"column":1},"end":{"line":2,"column":1}},"children":[{"type":"text","value":"The main functions for getting items return iterators, where pystac-client will handle retrieval of additional pages when needed. Note that one request is made for the first ten items, then a second request for the next ten.","position":{"start":{"line":2,"column":1},"end":{"line":2,"column":1}},"key":"rei38UVYp9"}],"key":"ZKngjQkuFW"}],"key":"hBGoSzpllS"},{"type":"block","kind":"notebook-code","data":{"tags":[]},"children":[{"type":"code","lang":"python","executable":true,"value":"coll_name = 'EO.ESA.DAT.SENTINEL-1.L1_GRD'\nsearch = cat.search(\n    max_items=10,\n    collections=[coll_name],\n    bbox=[-72.5,40.5,-72,41],\n    datetime=\"2023-09-09T00:00:00Z/2023-09-20T23:59:59Z\"\n)\n\ncoll_items = search.item_collection()\nconsole.print(f\"For collection {coll_name} we found {len(coll_items)} items\")","visibility":"show","key":"xWhBtRrLGK"},{"type":"output","id":"gq1KuVlhNSOKiew_GCuS_","data":[{"output_type":"display_data","metadata":{},"data":{"text/html":{"content":"<pre style=\"white-space:pre;overflow-x:auto;line-height:normal;font-family:Menlo,'DejaVu Sans Mono',consolas,'Courier New',monospace\">For collection EO.ESA.DAT.SENTINEL-<span style=\"color: #008080; text-decoration-color: #008080; font-weight: bold\">1.</span>L1_GRD we found <span style=\"color: #008080; text-decoration-color: #008080; font-weight: bold\">4</span> items\n</pre>\n","content_type":"text/html"},"text/plain":{"content":"For collection EO.ESA.DAT.SENTINEL-\u001b[1;36m1.\u001b[0mL1_GRD we found \u001b[1;36m4\u001b[0m items\n","content_type":"text/plain"}}}],"visibility":"show","key":"E7SxbTs74t"}],"visibility":"show","key":"mAk3zVXSM8"},{"type":"block","kind":"notebook-code","data":{"tags":[]},"children":[{"type":"code","lang":"python","executable":true,"value":"import geopandas\n\ndf = geopandas.GeoDataFrame.from_features(coll_items.to_dict(), crs=\"epsg:4326\")\ndf.head()\n\n","visibility":"show","key":"DrnJkQk6aP"},{"type":"output","id":"aXU7kC2twZWtv1lEnpn2O","data":[{"output_type":"execute_result","execution_count":10,"metadata":{},"data":{"text/html":{"content":"<div>\n<style scoped>\n    .dataframe tbody tr th:only-of-type {\n        vertical-align: middle;\n    }\n\n    .dataframe tbody tr th {\n        vertical-align: top;\n    }\n\n    .dataframe thead th {\n        text-align: right;\n    }\n</style>\n<table border=\"1\" class=\"dataframe\">\n  <thead>\n    <tr style=\"text-align: right;\">\n      <th></th>\n      <th>geometry</th>\n      <th>providers</th>\n      <th>datetime</th>\n      <th>start_datetime</th>\n      <th>end_datetime</th>\n      <th>updated</th>\n      <th>description</th>\n      <th>license</th>\n      <th>constellation</th>\n      <th>platform</th>\n      <th>...</th>\n      <th>dedl:productComposition</th>\n      <th>dedl:processorVersion</th>\n      <th>dedl:totalSlices</th>\n      <th>dedl:timeliness</th>\n      <th>dedl:productIdentifier</th>\n      <th>dedl:segmentStartTime</th>\n      <th>dedl:beginningDateTime</th>\n      <th>dedl:datatakeID</th>\n      <th>dedl:sliceProductFlag</th>\n      <th>dedl:uid</th>\n    </tr>\n  </thead>\n  <tbody>\n    <tr>\n      <th>0</th>\n      <td>POLYGON ((-72.73724 38.96255, -69.78494 39.365...</td>\n      <td>[{'name': 'dedl', 'description': 'DestineE Dat...</td>\n      <td>2023-09-09T22:43:00.442715Z</td>\n      <td>2023-09-09T22:43:00.442715Z</td>\n      <td>2023-09-09T22:43:25.441630Z</td>\n      <td>2023-09-10T03:08:53.951840Z</td>\n      <td>The [Sentinel-1](https://sentinel.esa.int/web/...</td>\n      <td>proprietary</td>\n      <td>SENTINEL-1</td>\n      <td>A</td>\n      <td>...</td>\n      <td>Slice</td>\n      <td>3.61</td>\n      <td>16</td>\n      <td>Fast-24h</td>\n      <td>/eodata/Sentinel-1/SAR/IW_GRDH_1S/2023/09/09/S...</td>\n      <td>2023-09-09T22:41:16.742000+00:00</td>\n      <td>2023-09-09T22:43:00.442715Z</td>\n      <td>396478</td>\n      <td>False</td>\n      <td>64caac74-8c5b-4f4d-9d3d-2d029b6e1ddc</td>\n    </tr>\n    <tr>\n      <th>1</th>\n      <td>POLYGON ((-73.11689 40.46453, -70.09798 40.866...</td>\n      <td>[{'name': 'dedl', 'description': 'DestineE Dat...</td>\n      <td>2023-09-09T22:43:25.443129Z</td>\n      <td>2023-09-09T22:43:25.443129Z</td>\n      <td>2023-09-09T22:43:50.442045Z</td>\n      <td>2023-09-10T02:57:33.550132Z</td>\n      <td>The [Sentinel-1](https://sentinel.esa.int/web/...</td>\n      <td>proprietary</td>\n      <td>SENTINEL-1</td>\n      <td>A</td>\n      <td>...</td>\n      <td>Slice</td>\n      <td>3.61</td>\n      <td>16</td>\n      <td>Fast-24h</td>\n      <td>/eodata/Sentinel-1/SAR/IW_GRDH_1S/2023/09/09/S...</td>\n      <td>2023-09-09T22:41:16.742000+00:00</td>\n      <td>2023-09-09T22:43:25.443129Z</td>\n      <td>396478</td>\n      <td>False</td>\n      <td>f97e0469-9ecc-466e-9706-f3a0a98a8426</td>\n    </tr>\n    <tr>\n      <th>2</th>\n      <td>POLYGON ((-74.73586 38.73753, -71.84171 39.134...</td>\n      <td>[{'name': 'dedl', 'description': 'DestineE Dat...</td>\n      <td>2023-09-14T22:51:10.454096Z</td>\n      <td>2023-09-14T22:51:10.454096Z</td>\n      <td>2023-09-14T22:51:35.452004Z</td>\n      <td>2023-09-15T01:30:12.125014Z</td>\n      <td>The [Sentinel-1](https://sentinel.esa.int/web/...</td>\n      <td>proprietary</td>\n      <td>SENTINEL-1</td>\n      <td>A</td>\n      <td>...</td>\n      <td>Slice</td>\n      <td>3.61</td>\n      <td>7</td>\n      <td>Fast-24h</td>\n      <td>/eodata/Sentinel-1/SAR/IW_GRDH_1S/2023/09/14/S...</td>\n      <td>2023-09-14T22:49:26.753000+00:00</td>\n      <td>2023-09-14T22:51:10.454096Z</td>\n      <td>397120</td>\n      <td>False</td>\n      <td>e81554b4-5784-4f0b-ad69-ef984b489b52</td>\n    </tr>\n    <tr>\n      <th>3</th>\n      <td>POLYGON ((-75.11328 40.2397, -72.15421 40.6353...</td>\n      <td>[{'name': 'dedl', 'description': 'DestineE Dat...</td>\n      <td>2023-09-14T22:51:35.453501Z</td>\n      <td>2023-09-14T22:51:35.453501Z</td>\n      <td>2023-09-14T22:52:00.452905Z</td>\n      <td>2023-09-15T01:28:26.349235Z</td>\n      <td>The [Sentinel-1](https://sentinel.esa.int/web/...</td>\n      <td>proprietary</td>\n      <td>SENTINEL-1</td>\n      <td>A</td>\n      <td>...</td>\n      <td>Slice</td>\n      <td>3.61</td>\n      <td>7</td>\n      <td>Fast-24h</td>\n      <td>/eodata/Sentinel-1/SAR/IW_GRDH_1S/2023/09/14/S...</td>\n      <td>2023-09-14T22:49:26.753000+00:00</td>\n      <td>2023-09-14T22:51:35.453501Z</td>\n      <td>397120</td>\n      <td>False</td>\n      <td>ac9a45a9-e210-4d84-824c-f1fe12e7a4ca</td>\n    </tr>\n  </tbody>\n</table>\n<p>4 rows × 38 columns</p>\n</div>","content_type":"text/html"},"text/plain":{"content":"                                            geometry  \\\n0  POLYGON ((-72.73724 38.96255, -69.78494 39.365...   \n1  POLYGON ((-73.11689 40.46453, -70.09798 40.866...   \n2  POLYGON ((-74.73586 38.73753, -71.84171 39.134...   \n3  POLYGON ((-75.11328 40.2397, -72.15421 40.6353...   \n\n                                           providers  \\\n0  [{'name': 'dedl', 'description': 'DestineE Dat...   \n1  [{'name': 'dedl', 'description': 'DestineE Dat...   \n2  [{'name': 'dedl', 'description': 'DestineE Dat...   \n3  [{'name': 'dedl', 'description': 'DestineE Dat...   \n\n                      datetime               start_datetime  \\\n0  2023-09-09T22:43:00.442715Z  2023-09-09T22:43:00.442715Z   \n1  2023-09-09T22:43:25.443129Z  2023-09-09T22:43:25.443129Z   \n2  2023-09-14T22:51:10.454096Z  2023-09-14T22:51:10.454096Z   \n3  2023-09-14T22:51:35.453501Z  2023-09-14T22:51:35.453501Z   \n\n                  end_datetime                      updated  \\\n0  2023-09-09T22:43:25.441630Z  2023-09-10T03:08:53.951840Z   \n1  2023-09-09T22:43:50.442045Z  2023-09-10T02:57:33.550132Z   \n2  2023-09-14T22:51:35.452004Z  2023-09-15T01:30:12.125014Z   \n3  2023-09-14T22:52:00.452905Z  2023-09-15T01:28:26.349235Z   \n\n                                         description      license  \\\n0  The [Sentinel-1](https://sentinel.esa.int/web/...  proprietary   \n1  The [Sentinel-1](https://sentinel.esa.int/web/...  proprietary   \n2  The [Sentinel-1](https://sentinel.esa.int/web/...  proprietary   \n3  The [Sentinel-1](https://sentinel.esa.int/web/...  proprietary   \n\n  constellation platform  ... dedl:productComposition dedl:processorVersion  \\\n0    SENTINEL-1        A  ...                   Slice                  3.61   \n1    SENTINEL-1        A  ...                   Slice                  3.61   \n2    SENTINEL-1        A  ...                   Slice                  3.61   \n3    SENTINEL-1        A  ...                   Slice                  3.61   \n\n  dedl:totalSlices dedl:timeliness  \\\n0               16        Fast-24h   \n1               16        Fast-24h   \n2                7        Fast-24h   \n3                7        Fast-24h   \n\n                              dedl:productIdentifier  \\\n0  /eodata/Sentinel-1/SAR/IW_GRDH_1S/2023/09/09/S...   \n1  /eodata/Sentinel-1/SAR/IW_GRDH_1S/2023/09/09/S...   \n2  /eodata/Sentinel-1/SAR/IW_GRDH_1S/2023/09/14/S...   \n3  /eodata/Sentinel-1/SAR/IW_GRDH_1S/2023/09/14/S...   \n\n              dedl:segmentStartTime       dedl:beginningDateTime  \\\n0  2023-09-09T22:41:16.742000+00:00  2023-09-09T22:43:00.442715Z   \n1  2023-09-09T22:41:16.742000+00:00  2023-09-09T22:43:25.443129Z   \n2  2023-09-14T22:49:26.753000+00:00  2023-09-14T22:51:10.454096Z   \n3  2023-09-14T22:49:26.753000+00:00  2023-09-14T22:51:35.453501Z   \n\n  dedl:datatakeID dedl:sliceProductFlag                              dedl:uid  \n0          396478                 False  64caac74-8c5b-4f4d-9d3d-2d029b6e1ddc  \n1          396478                 False  f97e0469-9ecc-466e-9706-f3a0a98a8426  \n2          397120                 False  e81554b4-5784-4f0b-ad69-ef984b489b52  \n3          397120                 False  ac9a45a9-e210-4d84-824c-f1fe12e7a4ca  \n\n[4 rows x 38 columns]","content_type":"text/plain"}}}],"visibility":"show","key":"deqwKvxH4W"}],"visibility":"show","key":"ioOqfH0AMs"},{"type":"block","kind":"notebook-content","children":[{"type":"heading","depth":2,"position":{"start":{"line":1,"column":1},"end":{"line":1,"column":1}},"children":[{"type":"text","value":"Inspect STAC assets of an item","position":{"start":{"line":1,"column":1},"end":{"line":1,"column":1}},"key":"eL87VwcPbY"}],"identifier":"inspect-stac-assets-of-an-item","label":"Inspect STAC assets of an item","html_id":"inspect-stac-assets-of-an-item","implicit":true,"key":"sa7K2JyoUX"}],"key":"aphlF9435q"},{"type":"block","kind":"notebook-code","data":{"tags":[]},"children":[{"type":"code","lang":"python","executable":true,"value":"import rich.table\n\nselected_item = coll_items[3]\n\ntable = rich.table.Table(title=\"Assets in STAC Item\")\ntable.add_column(\"Asset Key\", style=\"cyan\", no_wrap=True)\ntable.add_column(\"Description\")\nfor asset_key, asset in selected_item.assets.items():\n    table.add_row(asset_key, asset.title)\n\nconsole.print(table)","visibility":"show","key":"BoUyUhpWg5"},{"type":"output","id":"M6g5QwPLxzq6DMkaWcqFp","data":[{"output_type":"display_data","metadata":{},"data":{"text/html":{"content":"<pre style=\"white-space:pre;overflow-x:auto;line-height:normal;font-family:Menlo,'DejaVu Sans Mono',consolas,'Courier New',monospace\"><span style=\"font-style: italic\">                                                Assets in STAC Item                                                </span>\n┏━━━━━━━━━━━━━━━━━━━━━━━━━━━━━━━━━━━━━━━━━━━━━━━━━━━━━━━━━━━━━━━━━━━━━━━━━━━━━━━━━━━━━━━━━━━━━━━━━━━━━┳━━━━━━━━━━━┓\n┃<span style=\"font-weight: bold\"> Asset Key                                                                                           </span>┃<span style=\"font-weight: bold\"> Descript… </span>┃\n┡━━━━━━━━━━━━━━━━━━━━━━━━━━━━━━━━━━━━━━━━━━━━━━━━━━━━━━━━━━━━━━━━━━━━━━━━━━━━━━━━━━━━━━━━━━━━━━━━━━━━━╇━━━━━━━━━━━┩\n│<span style=\"color: #008080; text-decoration-color: #008080\"> downloadLink                                                                                        </span>│ Download  │\n│<span style=\"color: #008080; text-decoration-color: #008080\">                                                                                                     </span>│ link      │\n│<span style=\"color: #008080; text-decoration-color: #008080\"> S1A_IW_GRDH_1SDV_20230914T225135_20230914T225200_050330_060F40_9F54.SAFE-report-20230915T011838.pdf </span>│ S1A_IW_G… │\n│<span style=\"color: #008080; text-decoration-color: #008080\"> calibration-s1a-iw-grd-vh-20230914t225135-20230914t225200-050330-060f40-002.xml                     </span>│ calibrat… │\n│<span style=\"color: #008080; text-decoration-color: #008080\"> calibration-s1a-iw-grd-vv-20230914t225135-20230914t225200-050330-060f40-001.xml                     </span>│ calibrat… │\n│<span style=\"color: #008080; text-decoration-color: #008080\"> noise-s1a-iw-grd-vh-20230914t225135-20230914t225200-050330-060f40-002.xml                           </span>│ noise-s1… │\n│<span style=\"color: #008080; text-decoration-color: #008080\"> noise-s1a-iw-grd-vv-20230914t225135-20230914t225200-050330-060f40-001.xml                           </span>│ noise-s1… │\n│<span style=\"color: #008080; text-decoration-color: #008080\"> rfi-s1a-iw-grd-vh-20230914t225135-20230914t225200-050330-060f40-002.xml                             </span>│ rfi-s1a-… │\n│<span style=\"color: #008080; text-decoration-color: #008080\"> rfi-s1a-iw-grd-vv-20230914t225135-20230914t225200-050330-060f40-001.xml                             </span>│ rfi-s1a-… │\n│<span style=\"color: #008080; text-decoration-color: #008080\"> s1a-iw-grd-vh-20230914t225135-20230914t225200-050330-060f40-002.xml                                 </span>│ s1a-iw-g… │\n│<span style=\"color: #008080; text-decoration-color: #008080\"> s1a-iw-grd-vv-20230914t225135-20230914t225200-050330-060f40-001.xml                                 </span>│ s1a-iw-g… │\n│<span style=\"color: #008080; text-decoration-color: #008080\"> manifest.safe                                                                                       </span>│ manifest… │\n│<span style=\"color: #008080; text-decoration-color: #008080\"> s1a-iw-grd-vh-20230914t225135-20230914t225200-050330-060f40-002.tiff                                </span>│ s1a-iw-g… │\n│<span style=\"color: #008080; text-decoration-color: #008080\"> s1a-iw-grd-vv-20230914t225135-20230914t225200-050330-060f40-001.tiff                                </span>│ s1a-iw-g… │\n│<span style=\"color: #008080; text-decoration-color: #008080\"> logo.png                                                                                            </span>│ logo.png  │\n│<span style=\"color: #008080; text-decoration-color: #008080\"> map-overlay.kml                                                                                     </span>│ map-over… │\n│<span style=\"color: #008080; text-decoration-color: #008080\"> product-preview.html                                                                                </span>│ product-… │\n│<span style=\"color: #008080; text-decoration-color: #008080\"> quick-look.png                                                                                      </span>│ quick-lo… │\n│<span style=\"color: #008080; text-decoration-color: #008080\"> thumbnail.png                                                                                       </span>│ thumbnai… │\n│<span style=\"color: #008080; text-decoration-color: #008080\"> s1-level-1-calibration.xsd                                                                          </span>│ s1-level… │\n│<span style=\"color: #008080; text-decoration-color: #008080\"> s1-level-1-measurement.xsd                                                                          </span>│ s1-level… │\n│<span style=\"color: #008080; text-decoration-color: #008080\"> s1-level-1-noise.xsd                                                                                </span>│ s1-level… │\n│<span style=\"color: #008080; text-decoration-color: #008080\"> s1-level-1-product.xsd                                                                              </span>│ s1-level… │\n│<span style=\"color: #008080; text-decoration-color: #008080\"> s1-level-1-quicklook.xsd                                                                            </span>│ s1-level… │\n│<span style=\"color: #008080; text-decoration-color: #008080\"> s1-level-1-rfi.xsd                                                                                  </span>│ s1-level… │\n│<span style=\"color: #008080; text-decoration-color: #008080\"> s1-map-overlay.xsd                                                                                  </span>│ s1-map-o… │\n│<span style=\"color: #008080; text-decoration-color: #008080\"> s1-object-types.xsd                                                                                 </span>│ s1-objec… │\n│<span style=\"color: #008080; text-decoration-color: #008080\"> s1-product-preview.xsd                                                                              </span>│ s1-produ… │\n│<span style=\"color: #008080; text-decoration-color: #008080\"> thumbnail                                                                                           </span>│ Thumbnail │\n└─────────────────────────────────────────────────────────────────────────────────────────────────────┴───────────┘\n</pre>\n","content_type":"text/html"},"text/plain":{"content":"\u001b[3m                                                Assets in STAC Item                                                \u001b[0m\n┏━━━━━━━━━━━━━━━━━━━━━━━━━━━━━━━━━━━━━━━━━━━━━━━━━━━━━━━━━━━━━━━━━━━━━━━━━━━━━━━━━━━━━━━━━━━━━━━━━━━━━┳━━━━━━━━━━━┓\n┃\u001b[1m \u001b[0m\u001b[1mAsset Key                                                                                          \u001b[0m\u001b[1m \u001b[0m┃\u001b[1m \u001b[0m\u001b[1mDescript…\u001b[0m\u001b[1m \u001b[0m┃\n┡━━━━━━━━━━━━━━━━━━━━━━━━━━━━━━━━━━━━━━━━━━━━━━━━━━━━━━━━━━━━━━━━━━━━━━━━━━━━━━━━━━━━━━━━━━━━━━━━━━━━━╇━━━━━━━━━━━┩\n│\u001b[36m \u001b[0m\u001b[36mdownloadLink                                                                                       \u001b[0m\u001b[36m \u001b[0m│ Download  │\n│\u001b[36m                                                                                                     \u001b[0m│ link      │\n│\u001b[36m \u001b[0m\u001b[36mS1A_IW_GRDH_1SDV_20230914T225135_20230914T225200_050330_060F40_9F54.SAFE-report-20230915T011838.pdf\u001b[0m\u001b[36m \u001b[0m│ S1A_IW_G… │\n│\u001b[36m \u001b[0m\u001b[36mcalibration-s1a-iw-grd-vh-20230914t225135-20230914t225200-050330-060f40-002.xml                    \u001b[0m\u001b[36m \u001b[0m│ calibrat… │\n│\u001b[36m \u001b[0m\u001b[36mcalibration-s1a-iw-grd-vv-20230914t225135-20230914t225200-050330-060f40-001.xml                    \u001b[0m\u001b[36m \u001b[0m│ calibrat… │\n│\u001b[36m \u001b[0m\u001b[36mnoise-s1a-iw-grd-vh-20230914t225135-20230914t225200-050330-060f40-002.xml                          \u001b[0m\u001b[36m \u001b[0m│ noise-s1… │\n│\u001b[36m \u001b[0m\u001b[36mnoise-s1a-iw-grd-vv-20230914t225135-20230914t225200-050330-060f40-001.xml                          \u001b[0m\u001b[36m \u001b[0m│ noise-s1… │\n│\u001b[36m \u001b[0m\u001b[36mrfi-s1a-iw-grd-vh-20230914t225135-20230914t225200-050330-060f40-002.xml                            \u001b[0m\u001b[36m \u001b[0m│ rfi-s1a-… │\n│\u001b[36m \u001b[0m\u001b[36mrfi-s1a-iw-grd-vv-20230914t225135-20230914t225200-050330-060f40-001.xml                            \u001b[0m\u001b[36m \u001b[0m│ rfi-s1a-… │\n│\u001b[36m \u001b[0m\u001b[36ms1a-iw-grd-vh-20230914t225135-20230914t225200-050330-060f40-002.xml                                \u001b[0m\u001b[36m \u001b[0m│ s1a-iw-g… │\n│\u001b[36m \u001b[0m\u001b[36ms1a-iw-grd-vv-20230914t225135-20230914t225200-050330-060f40-001.xml                                \u001b[0m\u001b[36m \u001b[0m│ s1a-iw-g… │\n│\u001b[36m \u001b[0m\u001b[36mmanifest.safe                                                                                      \u001b[0m\u001b[36m \u001b[0m│ manifest… │\n│\u001b[36m \u001b[0m\u001b[36ms1a-iw-grd-vh-20230914t225135-20230914t225200-050330-060f40-002.tiff                               \u001b[0m\u001b[36m \u001b[0m│ s1a-iw-g… │\n│\u001b[36m \u001b[0m\u001b[36ms1a-iw-grd-vv-20230914t225135-20230914t225200-050330-060f40-001.tiff                               \u001b[0m\u001b[36m \u001b[0m│ s1a-iw-g… │\n│\u001b[36m \u001b[0m\u001b[36mlogo.png                                                                                           \u001b[0m\u001b[36m \u001b[0m│ logo.png  │\n│\u001b[36m \u001b[0m\u001b[36mmap-overlay.kml                                                                                    \u001b[0m\u001b[36m \u001b[0m│ map-over… │\n│\u001b[36m \u001b[0m\u001b[36mproduct-preview.html                                                                               \u001b[0m\u001b[36m \u001b[0m│ product-… │\n│\u001b[36m \u001b[0m\u001b[36mquick-look.png                                                                                     \u001b[0m\u001b[36m \u001b[0m│ quick-lo… │\n│\u001b[36m \u001b[0m\u001b[36mthumbnail.png                                                                                      \u001b[0m\u001b[36m \u001b[0m│ thumbnai… │\n│\u001b[36m \u001b[0m\u001b[36ms1-level-1-calibration.xsd                                                                         \u001b[0m\u001b[36m \u001b[0m│ s1-level… │\n│\u001b[36m \u001b[0m\u001b[36ms1-level-1-measurement.xsd                                                                         \u001b[0m\u001b[36m \u001b[0m│ s1-level… │\n│\u001b[36m \u001b[0m\u001b[36ms1-level-1-noise.xsd                                                                               \u001b[0m\u001b[36m \u001b[0m│ s1-level… │\n│\u001b[36m \u001b[0m\u001b[36ms1-level-1-product.xsd                                                                             \u001b[0m\u001b[36m \u001b[0m│ s1-level… │\n│\u001b[36m \u001b[0m\u001b[36ms1-level-1-quicklook.xsd                                                                           \u001b[0m\u001b[36m \u001b[0m│ s1-level… │\n│\u001b[36m \u001b[0m\u001b[36ms1-level-1-rfi.xsd                                                                                 \u001b[0m\u001b[36m \u001b[0m│ s1-level… │\n│\u001b[36m \u001b[0m\u001b[36ms1-map-overlay.xsd                                                                                 \u001b[0m\u001b[36m \u001b[0m│ s1-map-o… │\n│\u001b[36m \u001b[0m\u001b[36ms1-object-types.xsd                                                                                \u001b[0m\u001b[36m \u001b[0m│ s1-objec… │\n│\u001b[36m \u001b[0m\u001b[36ms1-product-preview.xsd                                                                             \u001b[0m\u001b[36m \u001b[0m│ s1-produ… │\n│\u001b[36m \u001b[0m\u001b[36mthumbnail                                                                                          \u001b[0m\u001b[36m \u001b[0m│ Thumbnail │\n└─────────────────────────────────────────────────────────────────────────────────────────────────────┴───────────┘\n","content_type":"text/plain"}}}],"visibility":"show","key":"ZfgGwMvEvZ"}],"visibility":"show","key":"wNIPfZQa0K"},{"type":"block","kind":"notebook-code","data":{"tags":[]},"children":[{"type":"code","lang":"python","executable":true,"value":"from IPython.display import Image\n\nImage(url=selected_item.assets[\"thumbnail\"].href, width=500)","visibility":"show","key":"JQDFyzTXsj"},{"type":"output","id":"PNQRc8ZhWBLb2JUIeinFA","data":[{"output_type":"execute_result","execution_count":12,"metadata":{},"data":{"text/html":{"content":"<img src=\"https://datahub.creodias.eu/odata/v1/Assets(74e634c0-b61a-499b-acea-57168a4981fd)/$value\" width=\"500\"/>","content_type":"text/html"},"text/plain":{"content":"<IPython.core.display.Image object>","content_type":"text/plain"}}}],"visibility":"show","key":"JWV3KibsH9"}],"visibility":"show","key":"GJisLThYyn"},{"type":"block","kind":"notebook-code","data":{"tags":[]},"children":[{"type":"code","lang":"python","executable":true,"value":"down_uri = selected_item.assets[\"downloadLink\"].href\nconsole.print(f\"Download link of asset is {down_uri}\")","visibility":"show","key":"OPWaH2CGe9"},{"type":"output","id":"33UpDviP45KO8_7BrCGbA","data":[{"output_type":"display_data","metadata":{},"data":{"text/html":{"content":"<pre style=\"white-space:pre;overflow-x:auto;line-height:normal;font-family:Menlo,'DejaVu Sans Mono',consolas,'Courier New',monospace\">Download link of asset is \n<span style=\"color: #0000ff; text-decoration-color: #0000ff; text-decoration: underline\">https://hda.data.destination-earth.eu/stac/collections/EO.ESA.DAT.SENTINEL-1.L1_GRD/items/S1A_IW_GRDH_1SDV_20230914</span>\n<span style=\"color: #0000ff; text-decoration-color: #0000ff; text-decoration: underline\">T225135_20230914T225200_050330_060F40_9F54/download?provider=dedl</span>\n</pre>\n","content_type":"text/html"},"text/plain":{"content":"Download link of asset is \n\u001b[4;94mhttps://hda.data.destination-earth.eu/stac/collections/EO.ESA.DAT.SENTINEL-1.L1_GRD/items/S1A_IW_GRDH_1SDV_20230914\u001b[0m\n\u001b[4;94mT225135_20230914T225200_050330_060F40_9F54/download?\u001b[0m\u001b[4;94mprovider\u001b[0m\u001b[4;94m=\u001b[0m\u001b[4;94mdedl\u001b[0m\n","content_type":"text/plain"}}}],"visibility":"show","key":"iFs5FMMJlh"}],"visibility":"show","key":"zFKmD8g72B"},{"type":"block","kind":"notebook-content","children":[{"type":"heading","depth":3,"position":{"start":{"line":1,"column":1},"end":{"line":1,"column":1}},"children":[{"type":"text","value":"Download asset to JupyterLab","position":{"start":{"line":1,"column":1},"end":{"line":1,"column":1}},"key":"B4fBTqhRtO"}],"identifier":"download-asset-to-jupyterlab","label":"Download asset to JupyterLab","html_id":"download-asset-to-jupyterlab","implicit":true,"key":"VH0ljyUjnX"}],"key":"whFBCVfJVB"},{"type":"block","kind":"notebook-code","data":{"tags":[]},"children":[{"type":"code","lang":"python","executable":true,"value":"selected_item.id","visibility":"show","key":"FoqwxkB69v"},{"type":"output","id":"ODr2AKJ4Aj5y3yRlyyMuz","data":[{"output_type":"execute_result","execution_count":14,"metadata":{},"data":{"text/plain":{"content":"'S1A_IW_GRDH_1SDV_20230914T225135_20230914T225200_050330_060F40_9F54'","content_type":"text/plain"}}}],"visibility":"show","key":"h3kJQUA3MU"}],"visibility":"show","key":"MnWX2V5xtp"},{"type":"block","kind":"notebook-code","data":{"tags":[]},"children":[{"type":"code","lang":"python","executable":true,"value":"selected_item.assets[\"downloadLink\"]","visibility":"show","key":"vEeuShOti3"},{"type":"output","id":"uB_67i3gmCP3tayRoVsiz","data":[{"output_type":"execute_result","execution_count":15,"metadata":{},"data":{"text/html":{"content":"\n\n<style>\n.pystac-summary {\n    cursor: pointer;\n    display: list-item;\n    list-style: revert;\n    margin-bottom: 0 !important;\n\n    .pystac-l {\n        padding-left: 0.5em;\n        color: rgb(64, 128, 128);\n        font-style: italic;\n    }\n}\n.pystac-row {\n    overflow-wrap: break-word;\n    padding-left: .825em;\n\n    .pystac-k {\n        display: inline-block;\n        margin: 0px 0.5em 0px 0px;\n    }\n    .pystac-v {\n        color: rgb(186, 33, 33);\n    }\n}\n.pystac-k {\n    color: rgb(0, 128, 0);\n    font-weight: 700;\n}\n</style>\n<div class=\"jp-RenderedJSON jp-mod-trusted jp-OutputArea-output\">\n    <div class=\"container\" style=\"line-height: normal;\">\n        <ul style=\"padding: 0px; margin: 0px; list-style: none; display: block;\">\n            \n                \n                    \n        <li class=\"pystac-row\">\n            <span class=\"pystac-k\">href</span>\n            <span class=\"pystac-v\">\"https://hda.data.destination-earth.eu/stac/collections/EO.ESA.DAT.SENTINEL-1.L1_GRD/items/S1A_IW_GRDH_1SDV_20230914T225135_20230914T225200_050330_060F40_9F54/download?provider=dedl\"</span>\n        </li>\n    \n                \n            \n                \n                    \n        <li class=\"pystac-row\">\n            <span class=\"pystac-k\">type</span>\n            <span class=\"pystac-v\">\"application/zip\"</span>\n        </li>\n    \n                \n            \n                \n                    \n        <li class=\"pystac-row\">\n            <span class=\"pystac-k\">title</span>\n            <span class=\"pystac-v\">\"Download link\"</span>\n        </li>\n    \n                \n            \n                \n                    \n        <li><details>\n            <summary class=\"pystac-summary\"><span class=\"pystac-k\">alternate</span></summary>\n            <ul style=\"margin: 0px; padding: 0px 0px 0px 1.75em; list-style: none; display: block;\">\n        \n            \n                \n        <li><details>\n            <summary class=\"pystac-summary\"><span class=\"pystac-k\">origin</span></summary>\n            <ul style=\"margin: 0px; padding: 0px 0px 0px 1.75em; list-style: none; display: block;\">\n        \n            \n                \n        <li class=\"pystac-row\">\n            <span class=\"pystac-k\">title</span>\n            <span class=\"pystac-v\">\"Origin asset link\"</span>\n        </li>\n    \n            \n        \n            \n                \n        <li class=\"pystac-row\">\n            <span class=\"pystac-k\">href</span>\n            <span class=\"pystac-v\">\"https://zipper.creodias.eu/odata/v1/Products(ac9a45a9-e210-4d84-824c-f1fe12e7a4ca)/$value\"</span>\n        </li>\n    \n            \n        \n    </ul>\n        </details></li>\n    \n            \n        \n    </ul>\n        </details></li>\n    \n                \n            \n                \n                    \n        <li class=\"pystac-row\">\n            <span class=\"pystac-k\">storage:tier</span>\n            <span class=\"pystac-v\">\"ONLINE\"</span>\n        </li>\n    \n                \n            \n        </ul>\n    </div>\n</div>","content_type":"text/html"},"text/plain":{"content":"<Asset href=https://hda.data.destination-earth.eu/stac/collections/EO.ESA.DAT.SENTINEL-1.L1_GRD/items/S1A_IW_GRDH_1SDV_20230914T225135_20230914T225200_050330_060F40_9F54/download?provider=dedl>","content_type":"text/plain"}}}],"visibility":"show","key":"hNo8HQSeNm"}],"visibility":"show","key":"MrGDSLBHBv"},{"type":"block","kind":"notebook-code","data":{"tags":[]},"children":[{"type":"code","lang":"python","executable":true,"value":"# Make http request for remote file data\ndata = requests.get(selected_item.assets[\"downloadLink\"].href,\n                   headers=auth_headers)\nmtype = selected_item.assets[\"downloadLink\"].media_type.split(\"/\")[1]\n# Save file data to local copy\nwith open(f\"{selected_item.id}.{mtype}\", 'wb')as file:\n    file.write(data.content)","visibility":"show","key":"bJaFanE7fS"},{"type":"output","id":"5juWKDU2geu3R79PwpT9d","data":[],"visibility":"show","key":"Om5FIF7iby"}],"visibility":"show","key":"UjSY3uuqdq"}],"key":"gd8ZfRoawi"},"references":{"cite":{"order":[],"data":{}}}}