{"version":2,"kind":"Article","sha256":"9526da167b4657754c6b4a943518902aa272cb935eb252f40485669a7adc58cd","slug":"readme","location":"/HDA/README.md","dependencies":[],"frontmatter":{"title":"DestinE Harmonised Data Access (HDA)","content_includes_title":true,"numbering":{"title":{"offset":1}},"thumbnail":"/DestinE-banner-6c2eb150e9d965f57a9ba99945269d56.jpg","exports":[{"format":"md","filename":"README.md","url":"/README-8aa56bbcede2e19bac2fcc9b5cb8d6c6.md"}]},"mdast":{"type":"root","children":[{"type":"block","children":[{"type":"paragraph","position":{"start":{"line":1,"column":1},"end":{"line":3,"column":1}},"children":[{"type":"image","url":"/DestinE-banner-6c2eb150e9d965f57a9ba99945269d56.jpg","alt":"Destination Earth banner","key":"qtMAPuQYuK","urlSource":"../img/DestinE-banner.jpg"}],"key":"qWvLt9Cjdk"},{"type":"heading","depth":1,"position":{"start":{"line":5,"column":1},"end":{"line":5,"column":1}},"children":[{"type":"text","value":"DestinE Harmonised Data Access (HDA)","position":{"start":{"line":5,"column":1},"end":{"line":5,"column":1}},"key":"TDuxLWodyT"}],"identifier":"destine-harmonised-data-access-hda","label":"DestinE Harmonised Data Access (HDA)","html_id":"destine-harmonised-data-access-hda","implicit":true,"key":"vGS9B8YohB"},{"type":"paragraph","position":{"start":{"line":7,"column":1},"end":{"line":8,"column":1}},"children":[{"type":"image","style":{"float":"left","width":"5%"},"url":"/EUMETSAT-icon-273fc63bad2e241e36cd3193da7b8834.png","key":"hlBsvB0zxH","urlSource":"../img/EUMETSAT-icon.png"},{"type":"text","value":" ","position":{"start":{"line":7,"column":1},"end":{"line":7,"column":1}},"key":"tUGYfAgZfS"},{"type":"strong","position":{"start":{"line":7,"column":1},"end":{"line":7,"column":1}},"children":[{"type":"text","value":"Author:","position":{"start":{"line":7,"column":1},"end":{"line":7,"column":1}},"key":"Ls7K0m4JMc"}],"key":"lmHjPlmSkj"},{"type":"text","value":" EUMETSAT\n","position":{"start":{"line":7,"column":1},"end":{"line":7,"column":1}},"key":"NvA6iw2KJF"},{"type":"break","key":"Nb2u9D4lKP"}],"key":"mEd3R7i6ww"},{"type":"paragraph","position":{"start":{"line":10,"column":1},"end":{"line":10,"column":1}},"children":[{"type":"text","value":"Materials to learn how to use Harmonised Data Access API and examples","position":{"start":{"line":10,"column":1},"end":{"line":10,"column":1}},"key":"fTL3R3D1wT"}],"key":"IBpGGtPlr1"},{"type":"paragraph","position":{"start":{"line":12,"column":1},"end":{"line":12,"column":1}},"children":[{"type":"strong","position":{"start":{"line":12,"column":1},"end":{"line":12,"column":1}},"children":[{"type":"text","value":"Notebooks","position":{"start":{"line":12,"column":1},"end":{"line":12,"column":1}},"key":"QrmPgD76so"}],"key":"iB3Z8afp9d"}],"key":"nbR2tOKXKg"},{"type":"list","ordered":false,"spread":false,"position":{"start":{"line":13,"column":1},"end":{"line":34,"column":1}},"children":[{"type":"listItem","spread":true,"position":{"start":{"line":13,"column":1},"end":{"line":13,"column":1}},"children":[{"type":"link","url":"https://github.com/destination-earth/DestinE-DataLake-Lab/blob/main/HDA/REST/HDA-REST-quick-start.ipynb","position":{"start":{"line":13,"column":1},"end":{"line":13,"column":1}},"children":[{"type":"text","value":"How to use the HDA API sending a few HTTP requests, quick-start","position":{"start":{"line":13,"column":1},"end":{"line":13,"column":1}},"key":"KQlgYkPHFS"}],"urlSource":"https://github.com/destination-earth/DestinE-DataLake-Lab/blob/main/HDA/REST/HDA-REST-quick-start.ipynb","data":{"kind":"file","org":"destination-earth","repo":"DestinE-DataLake-Lab","reference":"main","file":"HDA/REST/HDA-REST-quick-start.ipynb","raw":"https://raw.githubusercontent.com/destination-earth/DestinE-DataLake-Lab/main/HDA/REST/HDA-REST-quick-start.ipynb"},"internal":false,"protocol":"github","key":"XqFxn1hBuw"}],"key":"z18moJB0Fu"},{"type":"listItem","spread":true,"position":{"start":{"line":14,"column":1},"end":{"line":14,"column":1}},"children":[{"type":"link","url":"https://github.com/destination-earth/DestinE-DataLake-Lab/blob/main/HDA/REST/HDA-REST-full-version.ipynb","position":{"start":{"line":14,"column":1},"end":{"line":14,"column":1}},"children":[{"type":"text","value":"How to use the HDA API sending a few HTTP requests, full-version","position":{"start":{"line":14,"column":1},"end":{"line":14,"column":1}},"key":"mjq1EMpm3K"}],"urlSource":"https://github.com/destination-earth/DestinE-DataLake-Lab/blob/main/HDA/REST/HDA-REST-full-version.ipynb","data":{"kind":"file","org":"destination-earth","repo":"DestinE-DataLake-Lab","reference":"main","file":"HDA/REST/HDA-REST-full-version.ipynb","raw":"https://raw.githubusercontent.com/destination-earth/DestinE-DataLake-Lab/main/HDA/REST/HDA-REST-full-version.ipynb"},"internal":false,"protocol":"github","key":"JntxkK95H1"}],"key":"oCewKsKcIf"},{"type":"listItem","spread":true,"position":{"start":{"line":15,"column":1},"end":{"line":15,"column":1}},"children":[{"type":"link","url":"https://github.com/destination-earth/DestinE-DataLake-Lab/blob/main/HDA/REST/HDA-REST-Queryables.ipynb","position":{"start":{"line":15,"column":1},"end":{"line":15,"column":1}},"children":[{"type":"text","value":"How to use the queryables HDA API to search and access C3S and Digital Twins data","position":{"start":{"line":15,"column":1},"end":{"line":15,"column":1}},"key":"v07Z4aQ3nF"}],"urlSource":"https://github.com/destination-earth/DestinE-DataLake-Lab/blob/main/HDA/REST/HDA-REST-Queryables.ipynb","data":{"kind":"file","org":"destination-earth","repo":"DestinE-DataLake-Lab","reference":"main","file":"HDA/REST/HDA-REST-Queryables.ipynb","raw":"https://raw.githubusercontent.com/destination-earth/DestinE-DataLake-Lab/main/HDA/REST/HDA-REST-Queryables.ipynb"},"internal":false,"protocol":"github","key":"edgI6IxNlf"}],"key":"MjyQ0rerMe"},{"type":"listItem","spread":true,"position":{"start":{"line":16,"column":1},"end":{"line":23,"column":1}},"children":[{"type":"emphasis","position":{"start":{"line":16,"column":1},"end":{"line":16,"column":1}},"children":[{"type":"text","value":"Discover, access and visualise ","position":{"start":{"line":16,"column":1},"end":{"line":16,"column":1}},"key":"CJSdlK9TRl"},{"type":"emphasis","position":{"start":{"line":16,"column":1},"end":{"line":16,"column":1}},"children":[{"type":"text","value":"Digital twins data","position":{"start":{"line":16,"column":1},"end":{"line":16,"column":1}},"key":"o2N3utqKuP"}],"key":"dA6a0meh3i"},{"type":"text","value":" with HDA","position":{"start":{"line":16,"column":1},"end":{"line":16,"column":1}},"key":"vM3ZXWfV1N"}],"key":"nEBrYteudV"},{"type":"list","ordered":false,"spread":false,"position":{"start":{"line":17,"column":1},"end":{"line":23,"column":1}},"children":[{"type":"listItem","spread":true,"position":{"start":{"line":17,"column":1},"end":{"line":17,"column":1}},"children":[{"type":"link","url":"https://github.com/destination-earth/DestinE-DataLake-Lab/blob/main/HDA/DestinE%20Digital%20Twins/ClimateDT-ParameterPlotter.ipynb","position":{"start":{"line":17,"column":1},"end":{"line":17,"column":1}},"children":[{"type":"text","value":"Plot any Climate DT parameter","position":{"start":{"line":17,"column":1},"end":{"line":17,"column":1}},"key":"YuxKkL5qIw"}],"urlSource":"https://github.com/destination-earth/DestinE-DataLake-Lab/blob/main/HDA/DestinE%20Digital%20Twins/ClimateDT-ParameterPlotter.ipynb","data":{"kind":"file","org":"destination-earth","repo":"DestinE-DataLake-Lab","reference":"main","file":"HDA/DestinE%20Digital%20Twins/ClimateDT-ParameterPlotter.ipynb","raw":"https://raw.githubusercontent.com/destination-earth/DestinE-DataLake-Lab/main/HDA/DestinE%20Digital%20Twins/ClimateDT-ParameterPlotter.ipynb"},"internal":false,"protocol":"github","key":"jQkkytr7X7"}],"key":"GkKcPrWqBq"},{"type":"listItem","spread":true,"position":{"start":{"line":18,"column":1},"end":{"line":18,"column":1}},"children":[{"type":"link","url":"https://github.com/destination-earth/DestinE-DataLake-Lab/blob/main/HDA/DestinE%20Digital%20Twins/ExtremeDT-ParameterPlotter.ipynb","position":{"start":{"line":18,"column":1},"end":{"line":18,"column":1}},"children":[{"type":"text","value":"Plot any Extreme DT parameter","position":{"start":{"line":18,"column":1},"end":{"line":18,"column":1}},"key":"vq2NPo1pbP"}],"urlSource":"https://github.com/destination-earth/DestinE-DataLake-Lab/blob/main/HDA/DestinE%20Digital%20Twins/ExtremeDT-ParameterPlotter.ipynb","data":{"kind":"file","org":"destination-earth","repo":"DestinE-DataLake-Lab","reference":"main","file":"HDA/DestinE%20Digital%20Twins/ExtremeDT-ParameterPlotter.ipynb","raw":"https://raw.githubusercontent.com/destination-earth/DestinE-DataLake-Lab/main/HDA/DestinE%20Digital%20Twins/ExtremeDT-ParameterPlotter.ipynb"},"internal":false,"protocol":"github","key":"sfxKSeyrnw"}],"key":"QnRUiJqLXy"},{"type":"listItem","spread":true,"position":{"start":{"line":19,"column":1},"end":{"line":19,"column":1}},"children":[{"type":"link","url":"https://github.com/destination-earth/DestinE-DataLake-Lab/blob/main/HDA/DestinE%20Digital%20Twins/DEDL-HDA-EO.ECMWF.DAT.DT_CLIMATE.ipynb","position":{"start":{"line":19,"column":1},"end":{"line":19,"column":1}},"children":[{"type":"text","value":"Climate Adaptation Digital Twin data","position":{"start":{"line":19,"column":1},"end":{"line":19,"column":1}},"key":"b7ypTtQx8P"}],"urlSource":"https://github.com/destination-earth/DestinE-DataLake-Lab/blob/main/HDA/DestinE%20Digital%20Twins/DEDL-HDA-EO.ECMWF.DAT.DT_CLIMATE.ipynb","data":{"kind":"file","org":"destination-earth","repo":"DestinE-DataLake-Lab","reference":"main","file":"HDA/DestinE%20Digital%20Twins/DEDL-HDA-EO.ECMWF.DAT.DT_CLIMATE.ipynb","raw":"https://raw.githubusercontent.com/destination-earth/DestinE-DataLake-Lab/main/HDA/DestinE%20Digital%20Twins/DEDL-HDA-EO.ECMWF.DAT.DT_CLIMATE.ipynb"},"internal":false,"protocol":"github","key":"ypTotipZOd"}],"key":"j013SweK4Z"},{"type":"listItem","spread":true,"position":{"start":{"line":20,"column":1},"end":{"line":20,"column":1}},"children":[{"type":"link","url":"https://github.com/destination-earth/DestinE-DataLake-Lab/blob/main/HDA/DestinE%20Digital%20Twins/DEDL-HDA-EO.ECMWF.DAT.DT_CLIMATE-Series.ipynb","position":{"start":{"line":20,"column":1},"end":{"line":20,"column":1}},"children":[{"type":"text","value":"Climate Adaptation Digital Twin data - timeseries","position":{"start":{"line":20,"column":1},"end":{"line":20,"column":1}},"key":"By2gMK2wVA"}],"urlSource":"https://github.com/destination-earth/DestinE-DataLake-Lab/blob/main/HDA/DestinE%20Digital%20Twins/DEDL-HDA-EO.ECMWF.DAT.DT_CLIMATE-Series.ipynb","data":{"kind":"file","org":"destination-earth","repo":"DestinE-DataLake-Lab","reference":"main","file":"HDA/DestinE%20Digital%20Twins/DEDL-HDA-EO.ECMWF.DAT.DT_CLIMATE-Series.ipynb","raw":"https://raw.githubusercontent.com/destination-earth/DestinE-DataLake-Lab/main/HDA/DestinE%20Digital%20Twins/DEDL-HDA-EO.ECMWF.DAT.DT_CLIMATE-Series.ipynb"},"internal":false,"protocol":"github","key":"Vt94iTooMc"}],"key":"XmSFShYNcX"},{"type":"listItem","spread":true,"position":{"start":{"line":21,"column":1},"end":{"line":21,"column":1}},"children":[{"type":"link","url":"https://github.com/destination-earth/DestinE-DataLake-Lab/blob/main/HDA/DestinE%20Digital%20Twins/DEDL-HDA-EO.ECMWF.DAT.DT_EXTREMES-Series.ipynb","position":{"start":{"line":21,"column":1},"end":{"line":21,"column":1}},"children":[{"type":"text","value":"Extremes event  Digital Twin data - timeseries","position":{"start":{"line":21,"column":1},"end":{"line":21,"column":1}},"key":"yDs81yJkf1"}],"urlSource":"https://github.com/destination-earth/DestinE-DataLake-Lab/blob/main/HDA/DestinE%20Digital%20Twins/DEDL-HDA-EO.ECMWF.DAT.DT_EXTREMES-Series.ipynb","data":{"kind":"file","org":"destination-earth","repo":"DestinE-DataLake-Lab","reference":"main","file":"HDA/DestinE%20Digital%20Twins/DEDL-HDA-EO.ECMWF.DAT.DT_EXTREMES-Series.ipynb","raw":"https://raw.githubusercontent.com/destination-earth/DestinE-DataLake-Lab/main/HDA/DestinE%20Digital%20Twins/DEDL-HDA-EO.ECMWF.DAT.DT_EXTREMES-Series.ipynb"},"internal":false,"protocol":"github","key":"uekHeN6OTN"}],"key":"NDoU13yUE8"},{"type":"listItem","spread":true,"position":{"start":{"line":22,"column":1},"end":{"line":22,"column":1}},"children":[{"type":"link","url":"https://github.com/destination-earth/DestinE-DataLake-Lab/blob/main/HDA/DestinE%20Digital%20Twins/DEDL-HDA-EO.ECMWF.DAT.DT_EXTREMES.ipynb","position":{"start":{"line":22,"column":1},"end":{"line":22,"column":1}},"children":[{"type":"text","value":"Extremes event  Digital Twin data - xarray","position":{"start":{"line":22,"column":1},"end":{"line":22,"column":1}},"key":"BKoxX8726o"}],"urlSource":"https://github.com/destination-earth/DestinE-DataLake-Lab/blob/main/HDA/DestinE%20Digital%20Twins/DEDL-HDA-EO.ECMWF.DAT.DT_EXTREMES.ipynb","data":{"kind":"file","org":"destination-earth","repo":"DestinE-DataLake-Lab","reference":"main","file":"HDA/DestinE%20Digital%20Twins/DEDL-HDA-EO.ECMWF.DAT.DT_EXTREMES.ipynb","raw":"https://raw.githubusercontent.com/destination-earth/DestinE-DataLake-Lab/main/HDA/DestinE%20Digital%20Twins/DEDL-HDA-EO.ECMWF.DAT.DT_EXTREMES.ipynb"},"internal":false,"protocol":"github","key":"oGU5JDURUS"}],"key":"ThzQWfCmzp"},{"type":"listItem","spread":true,"position":{"start":{"line":23,"column":1},"end":{"line":23,"column":1}},"children":[{"type":"link","url":"https://github.com/destination-earth/DestinE-DataLake-Lab/blob/main/HDA/DestinE%20Digital%20Twins/ExtremeDT-dataAvailability.ipynb","position":{"start":{"line":23,"column":1},"end":{"line":23,"column":1}},"children":[{"type":"text","value":"Extremes event data availability - Aviso","position":{"start":{"line":23,"column":1},"end":{"line":23,"column":1}},"key":"VEqn9LLOrj"}],"urlSource":"https://github.com/destination-earth/DestinE-DataLake-Lab/blob/main/HDA/DestinE%20Digital%20Twins/ExtremeDT-dataAvailability.ipynb","data":{"kind":"file","org":"destination-earth","repo":"DestinE-DataLake-Lab","reference":"main","file":"HDA/DestinE%20Digital%20Twins/ExtremeDT-dataAvailability.ipynb","raw":"https://raw.githubusercontent.com/destination-earth/DestinE-DataLake-Lab/main/HDA/DestinE%20Digital%20Twins/ExtremeDT-dataAvailability.ipynb"},"internal":false,"protocol":"github","key":"UjdzLZxtF1"}],"key":"hwBSTDfHxZ"}],"key":"J6P1zTQroF"}],"key":"fYURLphyTc"},{"type":"listItem","spread":true,"position":{"start":{"line":24,"column":1},"end":{"line":27,"column":1}},"children":[{"type":"text","value":"Discover, access and visualise ","position":{"start":{"line":24,"column":1},"end":{"line":24,"column":1}},"key":"ZKtnc1gatO"},{"type":"emphasis","position":{"start":{"line":24,"column":1},"end":{"line":24,"column":1}},"children":[{"type":"text","value":"federated data","position":{"start":{"line":24,"column":1},"end":{"line":24,"column":1}},"key":"dkdHcVCEzy"}],"key":"IsnBlXBCTh"},{"type":"text","value":" with HDA","position":{"start":{"line":24,"column":1},"end":{"line":24,"column":1}},"key":"zfbUd50ttE"},{"type":"list","ordered":false,"spread":false,"position":{"start":{"line":25,"column":1},"end":{"line":27,"column":1}},"children":[{"type":"listItem","spread":true,"position":{"start":{"line":25,"column":1},"end":{"line":25,"column":1}},"children":[{"type":"link","url":"https://github.com/destination-earth/DestinE-DataLake-Lab/blob/main/HDA/EUM_data/DEDL-HDA-EO.EUM.DAT.SENTINEL-3.OL_1_ERR___.ipynb","position":{"start":{"line":25,"column":1},"end":{"line":25,"column":1}},"children":[{"type":"text","value":"Discover Sentinel-3 OLCI products example","position":{"start":{"line":25,"column":1},"end":{"line":25,"column":1}},"key":"Hkf7Wa3Xmh"}],"urlSource":"https://github.com/destination-earth/DestinE-DataLake-Lab/blob/main/HDA/EUM_data/DEDL-HDA-EO.EUM.DAT.SENTINEL-3.OL_1_ERR___.ipynb","data":{"kind":"file","org":"destination-earth","repo":"DestinE-DataLake-Lab","reference":"main","file":"HDA/EUM_data/DEDL-HDA-EO.EUM.DAT.SENTINEL-3.OL_1_ERR___.ipynb","raw":"https://raw.githubusercontent.com/destination-earth/DestinE-DataLake-Lab/main/HDA/EUM_data/DEDL-HDA-EO.EUM.DAT.SENTINEL-3.OL_1_ERR___.ipynb"},"internal":false,"protocol":"github","key":"GQV4K2XIco"}],"key":"uCKRWTA5QF"},{"type":"listItem","spread":true,"position":{"start":{"line":26,"column":1},"end":{"line":26,"column":1}},"children":[{"type":"link","url":"https://github.com/destination-earth/DestinE-DataLake-Lab/blob/main/HDA/EUM_data/DEDL-HDA-EO.EUM.DAT.METOP.AVHRRL1.ipynb","position":{"start":{"line":26,"column":1},"end":{"line":26,"column":1}},"children":[{"type":"text","value":"Discover AVHRR Metop products example","position":{"start":{"line":26,"column":1},"end":{"line":26,"column":1}},"key":"MKTsR2XkCZ"}],"urlSource":"https://github.com/destination-earth/DestinE-DataLake-Lab/blob/main/HDA/EUM_data/DEDL-HDA-EO.EUM.DAT.METOP.AVHRRL1.ipynb","data":{"kind":"file","org":"destination-earth","repo":"DestinE-DataLake-Lab","reference":"main","file":"HDA/EUM_data/DEDL-HDA-EO.EUM.DAT.METOP.AVHRRL1.ipynb","raw":"https://raw.githubusercontent.com/destination-earth/DestinE-DataLake-Lab/main/HDA/EUM_data/DEDL-HDA-EO.EUM.DAT.METOP.AVHRRL1.ipynb"},"internal":false,"protocol":"github","key":"GPyFLefRIT"}],"key":"Ny9nW9QaVE"},{"type":"listItem","spread":true,"position":{"start":{"line":27,"column":1},"end":{"line":27,"column":1}},"children":[{"type":"link","url":"https://github.com/destination-earth/DestinE-DataLake-Lab/blob/main/HDA/CDS_data/DEDL-HDA-EO.ECMWF.DAT.REANALYSIS_ERA5_SINGLE_LEVELS.ipynb","position":{"start":{"line":27,"column":1},"end":{"line":27,"column":1}},"children":[{"type":"text","value":"Discover and visualise ERA5 products example","position":{"start":{"line":27,"column":1},"end":{"line":27,"column":1}},"key":"BBoLYCfHb1"}],"urlSource":"https://github.com/destination-earth/DestinE-DataLake-Lab/blob/main/HDA/CDS_data/DEDL-HDA-EO.ECMWF.DAT.REANALYSIS_ERA5_SINGLE_LEVELS.ipynb","data":{"kind":"file","org":"destination-earth","repo":"DestinE-DataLake-Lab","reference":"main","file":"HDA/CDS_data/DEDL-HDA-EO.ECMWF.DAT.REANALYSIS_ERA5_SINGLE_LEVELS.ipynb","raw":"https://raw.githubusercontent.com/destination-earth/DestinE-DataLake-Lab/main/HDA/CDS_data/DEDL-HDA-EO.ECMWF.DAT.REANALYSIS_ERA5_SINGLE_LEVELS.ipynb"},"internal":false,"protocol":"github","key":"Sv298gJLqN"}],"key":"GTxZcB9IK3"}],"key":"nxah3GORFA"}],"key":"xGy8J0GOW0"},{"type":"listItem","spread":true,"position":{"start":{"line":28,"column":1},"end":{"line":30,"column":1}},"children":[{"type":"text","value":"Discover and access DEDL data using EODAG client","position":{"start":{"line":28,"column":1},"end":{"line":28,"column":1}},"key":"dJWZOVPNO0"},{"type":"list","ordered":false,"spread":false,"position":{"start":{"line":29,"column":1},"end":{"line":30,"column":1}},"children":[{"type":"listItem","spread":true,"position":{"start":{"line":29,"column":1},"end":{"line":29,"column":1}},"children":[{"type":"link","url":"https://github.com/destination-earth/DestinE-DataLake-Lab/blob/main/HDA/EODAG/HDA-EODAG-quick-start.ipynb","position":{"start":{"line":29,"column":1},"end":{"line":29,"column":1}},"children":[{"type":"text","value":"How to use the EODAG client with DEDL data, quick-start","position":{"start":{"line":29,"column":1},"end":{"line":29,"column":1}},"key":"imQvdtTYXe"}],"urlSource":"https://github.com/destination-earth/DestinE-DataLake-Lab/blob/main/HDA/EODAG/HDA-EODAG-quick-start.ipynb","data":{"kind":"file","org":"destination-earth","repo":"DestinE-DataLake-Lab","reference":"main","file":"HDA/EODAG/HDA-EODAG-quick-start.ipynb","raw":"https://raw.githubusercontent.com/destination-earth/DestinE-DataLake-Lab/main/HDA/EODAG/HDA-EODAG-quick-start.ipynb"},"internal":false,"protocol":"github","key":"Jri0owBA9K"}],"key":"o4APSfJjoa"},{"type":"listItem","spread":true,"position":{"start":{"line":30,"column":1},"end":{"line":30,"column":1}},"children":[{"type":"link","url":"https://github.com/destination-earth/DestinE-DataLake-Lab/blob/main/HDA/EODAG/HDA-EODAG-full-version.ipynb","position":{"start":{"line":30,"column":1},"end":{"line":30,"column":1}},"children":[{"type":"text","value":"How to use the EODAG client with DEDL data, full version","position":{"start":{"line":30,"column":1},"end":{"line":30,"column":1}},"key":"Y8Uso4m8YR"}],"urlSource":"https://github.com/destination-earth/DestinE-DataLake-Lab/blob/main/HDA/EODAG/HDA-EODAG-full-version.ipynb","data":{"kind":"file","org":"destination-earth","repo":"DestinE-DataLake-Lab","reference":"main","file":"HDA/EODAG/HDA-EODAG-full-version.ipynb","raw":"https://raw.githubusercontent.com/destination-earth/DestinE-DataLake-Lab/main/HDA/EODAG/HDA-EODAG-full-version.ipynb"},"internal":false,"protocol":"github","key":"U9FB7NnOBp"}],"key":"oJTHcIm1JY"}],"key":"xxd30xLW53"}],"key":"dggh6Mgexf"},{"type":"listItem","spread":true,"position":{"start":{"line":31,"column":1},"end":{"line":34,"column":1}},"children":[{"type":"text","value":"Access DEDL data using PySTAC client","position":{"start":{"line":31,"column":1},"end":{"line":31,"column":1}},"key":"oHLpU8GDGp"},{"type":"list","ordered":false,"spread":false,"position":{"start":{"line":32,"column":1},"end":{"line":34,"column":1}},"children":[{"type":"listItem","spread":true,"position":{"start":{"line":32,"column":1},"end":{"line":34,"column":1}},"children":[{"type":"link","url":"https://github.com/destination-earth/DestinE-DataLake-Lab/blob/main/HDA/PySTAC/HDA-PyStac-Client.ipynb","position":{"start":{"line":32,"column":1},"end":{"line":32,"column":1}},"children":[{"type":"text","value":"Discover and access DEDL data using PySTAC client","position":{"start":{"line":32,"column":1},"end":{"line":32,"column":1}},"key":"iARhAxNUwb"}],"urlSource":"https://github.com/destination-earth/DestinE-DataLake-Lab/blob/main/HDA/PySTAC/HDA-PyStac-Client.ipynb","data":{"kind":"file","org":"destination-earth","repo":"DestinE-DataLake-Lab","reference":"main","file":"HDA/PySTAC/HDA-PyStac-Client.ipynb","raw":"https://raw.githubusercontent.com/destination-earth/DestinE-DataLake-Lab/main/HDA/PySTAC/HDA-PyStac-Client.ipynb"},"internal":false,"protocol":"github","key":"qZQFrYGKLp"}],"key":"S4BohwwapE"}],"key":"QqFkdooWwx"}],"key":"oFNxb5TTjf"}],"key":"Sv5nieTmyo"},{"type":"paragraph","position":{"start":{"line":35,"column":1},"end":{"line":35,"column":1}},"children":[{"type":"text","value":"Further information available in DestinE Data Lake documentation: ","position":{"start":{"line":35,"column":1},"end":{"line":35,"column":1}},"key":"PR5xn2ibus"},{"type":"link","url":"https://destine-data-lake-docs.data.destination-earth.eu/en/latest/index.html","position":{"start":{"line":35,"column":1},"end":{"line":35,"column":1}},"children":[{"type":"text","value":"https://​destine​-data​-lake​-docs​.data​.destination​-earth​.eu​/en​/latest​/index​.html","position":{"start":{"line":35,"column":1},"end":{"line":35,"column":1}},"key":"A4A6ZEUZ5c"}],"urlSource":"https://destine-data-lake-docs.data.destination-earth.eu/en/latest/index.html","key":"yMRN4KHMM8"}],"key":"uuMtgR4zUd"},{"type":"blockquote","position":{"start":{"line":38,"column":1},"end":{"line":41,"column":1}},"children":[{"type":"paragraph","position":{"start":{"line":38,"column":1},"end":{"line":38,"column":1}},"children":[{"type":"strong","position":{"start":{"line":38,"column":1},"end":{"line":38,"column":1}},"children":[{"type":"text","value":"Additional ressources:","position":{"start":{"line":38,"column":1},"end":{"line":38,"column":1}},"key":"eunwDcFZmY"}],"key":"FcF37UT8w9"}],"key":"sYwaVheGLv"},{"type":"list","ordered":false,"spread":false,"position":{"start":{"line":39,"column":1},"end":{"line":41,"column":1}},"children":[{"type":"listItem","spread":true,"position":{"start":{"line":39,"column":1},"end":{"line":39,"column":1}},"children":[{"type":"text","value":"DestinE Data Portfolio: ","position":{"start":{"line":39,"column":1},"end":{"line":39,"column":1}},"key":"zplDEn435t"},{"type":"link","url":"https://hda.data.destination-earth.eu/ui/catalog","position":{"start":{"line":39,"column":1},"end":{"line":39,"column":1}},"children":[{"type":"text","value":"https://​hda​.data​.destination​-earth​.eu​/ui​/catalog","position":{"start":{"line":39,"column":1},"end":{"line":39,"column":1}},"key":"m5OoagHTQK"}],"urlSource":"https://hda.data.destination-earth.eu/ui/catalog","key":"winldxVqaG"}],"key":"kjGJWZEeV8"},{"type":"listItem","spread":true,"position":{"start":{"line":40,"column":1},"end":{"line":40,"column":1}},"children":[{"type":"text","value":"DataLake Priority services: ","position":{"start":{"line":40,"column":1},"end":{"line":40,"column":1}},"key":"fYnMMZgTRi"},{"type":"link","url":"https://hda.data.destination-earth.eu/ui/services","position":{"start":{"line":40,"column":1},"end":{"line":40,"column":1}},"children":[{"type":"text","value":"https://​hda​.data​.destination​-earth​.eu​/ui​/services","position":{"start":{"line":40,"column":1},"end":{"line":40,"column":1}},"key":"wVfDuL6oVq"}],"urlSource":"https://hda.data.destination-earth.eu/ui/services","key":"yBS1uLR0QO"}],"key":"ISNgLrkiAI"},{"type":"listItem","spread":true,"position":{"start":{"line":41,"column":1},"end":{"line":41,"column":1}},"children":[{"type":"text","value":"HDA SWAGGER UI: ","position":{"start":{"line":41,"column":1},"end":{"line":41,"column":1}},"key":"XNvZioNoZG"},{"type":"link","url":"https://hda.data.destination-earth.eu/docs/","position":{"start":{"line":41,"column":1},"end":{"line":41,"column":1}},"children":[{"type":"text","value":"https://​hda​.data​.destination​-earth​.eu​/docs/","position":{"start":{"line":41,"column":1},"end":{"line":41,"column":1}},"key":"aUvosCmQ4U"}],"urlSource":"https://hda.data.destination-earth.eu/docs/","key":"jMAPFrGh7Q"}],"key":"YuwSchm4I5"}],"key":"lxf7UF1SDK"}],"key":"fS4ewvZCU2"},{"type":"break","key":"XHgaemLbzc"},{"type":"paragraph","position":{"start":{"line":47,"column":1},"end":{"line":49,"column":1}},"children":[{"type":"strong","position":{"start":{"line":47,"column":1},"end":{"line":47,"column":1}},"children":[{"type":"text","value":"DestinE Core Platform Insula Users","position":{"start":{"line":47,"column":1},"end":{"line":47,"column":1}},"key":"wHmNAOWO8F"}],"key":"HAmSBTzOvv"},{"type":"text","value":"\n","position":{"start":{"line":47,"column":1},"end":{"line":47,"column":1}},"key":"Bsc2lXFUDZ"},{"type":"break","key":"OHt8zhUjBl"},{"type":"text","value":"\nPlease perform the following and select my_env kernel when running the provided Notebooks","position":{"start":{"line":47,"column":1},"end":{"line":47,"column":1}},"key":"dndi5RH9aa"},{"type":"break","key":"RsQEdXIYmZ"}],"key":"RajEj6OZsQ"},{"type":"paragraph","position":{"start":{"line":51,"column":1},"end":{"line":51,"column":1}},"children":[{"type":"text","value":"Open a terminal window (File, New, Terminal) and run the following commands in sequence:","position":{"start":{"line":51,"column":1},"end":{"line":51,"column":1}},"key":"iqkwZordSx"}],"key":"Iu73VuHhaQ"},{"type":"paragraph","position":{"start":{"line":53,"column":1},"end":{"line":53,"column":1}},"children":[{"type":"text","value":"Create a virtual environment:","position":{"start":{"line":53,"column":1},"end":{"line":53,"column":1}},"key":"mnRoQlstmZ"}],"key":"OetNNE08Kn"},{"type":"code","lang":"","value":" python -m venv /home/jovyan/my_env","position":{"start":{"line":55,"column":1},"end":{"line":55,"column":1}},"key":"AUVg1WzKjw"},{"type":"paragraph","position":{"start":{"line":57,"column":1},"end":{"line":57,"column":1}},"children":[{"type":"text","value":"Activate it:","position":{"start":{"line":57,"column":1},"end":{"line":57,"column":1}},"key":"r7SfS46iJM"}],"key":"ZWMaHkXNJK"},{"type":"code","lang":"","value":" source /home/jovyan/my_env/bin/activate","position":{"start":{"line":59,"column":1},"end":{"line":59,"column":1}},"key":"Jd1ri9SnS5"},{"type":"paragraph","position":{"start":{"line":61,"column":1},"end":{"line":61,"column":1}},"children":[{"type":"text","value":"Install required dependencies for this example Notebooks:","position":{"start":{"line":61,"column":1},"end":{"line":61,"column":1}},"key":"Ce0dZneqe3"}],"key":"KprKVkDA7Q"},{"type":"code","lang":"","value":" pip install -r /home/jovyan/datalake-lab/requirements.txt","position":{"start":{"line":63,"column":1},"end":{"line":63,"column":1}},"key":"PjkodrHZxv"},{"type":"paragraph","position":{"start":{"line":65,"column":1},"end":{"line":65,"column":1}},"children":[{"type":"text","value":"Verify the installation:","position":{"start":{"line":65,"column":1},"end":{"line":65,"column":1}},"key":"LNuOR8i1sO"}],"key":"s0C9aI7lg0"},{"type":"code","lang":"","value":" pip list | grep destinelab","position":{"start":{"line":67,"column":1},"end":{"line":67,"column":1}},"key":"uHVt01CBBv"},{"type":"paragraph","position":{"start":{"line":69,"column":1},"end":{"line":69,"column":1}},"children":[{"type":"text","value":"This should give:","position":{"start":{"line":69,"column":1},"end":{"line":69,"column":1}},"key":"ptOmjax9FL"}],"key":"L77wFvZZ9B"},{"type":"paragraph","position":{"start":{"line":71,"column":1},"end":{"line":71,"column":1}},"children":[{"type":"text","value":"destinelab         0.11","position":{"start":{"line":71,"column":1},"end":{"line":71,"column":1}},"key":"ArOcYUppjF"}],"key":"jHgazYJzOR"},{"type":"paragraph","position":{"start":{"line":73,"column":1},"end":{"line":73,"column":1}},"children":[{"type":"text","value":"Install kernel my_env. Run the command:","position":{"start":{"line":73,"column":1},"end":{"line":73,"column":1}},"key":"TecroI3lq4"}],"key":"qNdr8Cj2de"},{"type":"code","lang":"","value":" python -m ipykernel install --name my_env --user","position":{"start":{"line":75,"column":1},"end":{"line":75,"column":1}},"key":"jEwG1XQmVR"},{"type":"paragraph","position":{"start":{"line":77,"column":1},"end":{"line":77,"column":1}},"children":[{"type":"text","value":"Select the kernel my_env from the top-right menu of these notebooks.","position":{"start":{"line":77,"column":1},"end":{"line":77,"column":1}},"key":"ACWofxymFw"}],"key":"BI6XJJ0wb4"},{"type":"paragraph","position":{"start":{"line":79,"column":1},"end":{"line":79,"column":1}},"children":[{"type":"text","value":"Users who already have a previous version of the ‘my_env’ environment installed, should delete the kernel before running the steps above. To delete the my_env kernel please run the following command: ‘jupyter kernelspec uninstall my_env’ from a terminal window.","position":{"start":{"line":79,"column":1},"end":{"line":79,"column":1}},"key":"nhj7QTuhA9"}],"key":"PXowcEgqSZ"}],"key":"tNLgVxQHKI"}],"key":"Aqa7gvA9uo"},"references":{"cite":{"order":[],"data":{}}}}